odoo/addons/server_environment_files_sample/README.rst
odoo/addons/server_environment_files_sample/__init__.py
odoo/addons/server_environment_files_sample/__manifest__.py
odoo/addons/server_environment_files_sample/default/base.conf
odoo/addons/server_environment_files_sample/default/mytopic.conf
odoo/addons/server_environment_files_sample/preprod/mytopic.conf
odoo/addons/server_environment_files_sample/prod/base.conf
odoo/addons/server_environment_files_sample/prod/mytopic.conf
odoo/addons/server_environment_files_sample/readme/CONTRIBUTORS.rst
odoo/addons/server_environment_files_sample/readme/DESCRIPTION.rst
odoo/addons/server_environment_files_sample/readme/INSTALL.rst
odoo/addons/server_environment_files_sample/test/base.conf
odoo/addons/server_environment_files_sample/test/mytopic.conf
odoo11_addon_server_environment_files_sample-11.0.1.0.1.dist-info/METADATA
odoo11_addon_server_environment_files_sample-11.0.1.0.1.dist-info/WHEEL
odoo11_addon_server_environment_files_sample-11.0.1.0.1.dist-info/top_level.txt
odoo11_addon_server_environment_files_sample-11.0.1.0.1.dist-info/RECORD
